qupulse_mfli/__init__.py
qupulse_mfli/mfli.py
qupulse_mfli/numpy_magic.py
qupulse_mfli-0.0.1.dist-info/METADATA
qupulse_mfli-0.0.1.dist-info/WHEEL
qupulse_mfli-0.0.1.dist-info/licenses/LICENSE
qupulse_mfli-0.0.1.dist-info/RECORD
